faker_file/__init__.py
faker_file/base.py
faker_file/constants.py
faker_file/helpers.py
faker_file/registry.py
faker_file/cli/__init__.py
faker_file/cli/command.py
faker_file/cli/helpers.py
faker_file/contrib/__init__.py
faker_file/contrib/docx_file.py
faker_file/contrib/odt_file.py
faker_file/contrib/image/__init__.py
faker_file/contrib/image/imgkit_snippets.py
faker_file/contrib/image/pil_snippets.py
faker_file/contrib/image/weasyprint_snippets.py
faker_file/contrib/pdf_file/__init__.py
faker_file/contrib/pdf_file/pdfkit_snippets.py
faker_file/contrib/pdf_file/pil_snippets.py
faker_file/contrib/pdf_file/reportlab_snippets.py
faker_file/providers/__init__.py
faker_file/providers/augment_image_from_path.py
faker_file/providers/augment_random_image_from_dir.py
faker_file/providers/bin_file.py
faker_file/providers/bmp_file.py
faker_file/providers/csv_file.py
faker_file/providers/docx_file.py
faker_file/providers/eml_file.py
faker_file/providers/epub_file.py
faker_file/providers/file_from_path.py
faker_file/providers/file_from_url.py
faker_file/providers/generic_file.py
faker_file/providers/gif_file.py
faker_file/providers/ico_file.py
faker_file/providers/jpeg_file.py
faker_file/providers/json_file.py
faker_file/providers/odp_file.py
faker_file/providers/ods_file.py
faker_file/providers/odt_file.py
faker_file/providers/png_file.py
faker_file/providers/pptx_file.py
faker_file/providers/random_file_from_dir.py
faker_file/providers/rtf_file.py
faker_file/providers/svg_file.py
faker_file/providers/tar_file.py
faker_file/providers/tiff_file.py
faker_file/providers/txt_file.py
faker_file/providers/webp_file.py
faker_file/providers/xlsx_file.py
faker_file/providers/xml_file.py
faker_file/providers/zip_file.py
faker_file/providers/augment_file_from_dir/__init__.py
faker_file/providers/augment_file_from_dir/augmenters/__init__.py
faker_file/providers/augment_file_from_dir/augmenters/nlpaug_augmenter.py
faker_file-0.18.4.dist-info/LICENSE.rst
faker_file-0.18.4.dist-info/METADATA
faker_file-0.18.4.dist-info/WHEEL
faker_file-0.18.4.dist-info/entry_points.txt
faker_file-0.18.4.dist-info/top_level.txt
faker_file-0.18.4.dist-info/RECORD
