Metadata-Version: 2.1
Name: faker-file
Version: 0.18.4
Summary: Generate files with fake data.
Home-page: https://github.com/barseghyanartur/faker-file/
Author: Artur Barseghyan
Author-email: artur.barseghyan@gmail.com
License: MIT
Project-URL: Bug Tracker, https://github.com/barseghyanartur/faker-file/issues
Project-URL: Documentation, https://faker-file.readthedocs.io/
Project-URL: Source Code, https://github.com/barseghyanartur/faker-file
Project-URL: Changelog, https://faker-file.readthedocs.io/en/latest/changelog.html
Keywords: factories,fake file,fake files,fake-file-generator,fake-files-generator,faker,faker-file,file-generator,files,files-generator,test file,test files,test-file-generator,test-files-generator,testing
Classifier: Programming Language :: Python :: 3
Classifier: Programming Language :: Python :: 3.9
Classifier: Programming Language :: Python :: 3.10
Classifier: Programming Language :: Python :: 3.11
Classifier: Programming Language :: Python :: 3.12
Classifier: Environment :: Web Environment
Classifier: License :: OSI Approved :: MIT License
Classifier: Intended Audience :: Developers
Classifier: Operating System :: OS Independent
Classifier: Development Status :: 4 - Beta
Requires-Python: >=3.9
License-File: LICENSE.rst
Requires-Dist: Faker
Provides-Extra: all
Requires-Dist: Faker; extra == "all"
Requires-Dist: WeasyPrint; extra == "all"
Requires-Dist: imgkit; extra == "all"
Requires-Dist: odfpy; extra == "all"
Requires-Dist: openpyxl; extra == "all"
Requires-Dist: pathy[all]<0.12.0,>=0.10.0; extra == "all"
Requires-Dist: paramiko; extra == "all"
Requires-Dist: pdf2image; extra == "all"
Requires-Dist: pdfkit; extra == "all"
Requires-Dist: reportlab; extra == "all"
Requires-Dist: python-docx; extra == "all"
Requires-Dist: python-pptx; extra == "all"
Requires-Dist: tablib; extra == "all"
Requires-Dist: xml2epub; extra == "all"
Requires-Dist: gtts; extra == "all"
Requires-Dist: edge-tts; extra == "all"
Requires-Dist: nlpaug; extra == "all"
Requires-Dist: nltk; extra == "all"
Requires-Dist: textaugment; extra == "all"
Requires-Dist: textblob<0.18,>=0.17; extra == "all"
Requires-Dist: tika; extra == "all"
Requires-Dist: torch; extra == "all"
Requires-Dist: transformers; extra == "all"
Provides-Extra: azure
Requires-Dist: pathy[azure]<0.12.0,>=0.10.0; extra == "azure"
Provides-Extra: bmp
Requires-Dist: WeasyPrint; extra == "bmp"
Requires-Dist: pdf2image; extra == "bmp"
Provides-Extra: common
Requires-Dist: Faker; extra == "common"
Requires-Dist: WeasyPrint; extra == "common"
Requires-Dist: imgkit; extra == "common"
Requires-Dist: odfpy; extra == "common"
Requires-Dist: openpyxl; extra == "common"
Requires-Dist: pathy[all]<0.12.0,>=0.10.0; extra == "common"
Requires-Dist: paramiko; extra == "common"
Requires-Dist: pdf2image; extra == "common"
Requires-Dist: pdfkit; extra == "common"
Requires-Dist: reportlab; extra == "common"
Requires-Dist: python-docx; extra == "common"
Requires-Dist: python-pptx; extra == "common"
Requires-Dist: tablib; extra == "common"
Requires-Dist: xml2epub; extra == "common"
Requires-Dist: gtts; extra == "common"
Requires-Dist: edge-tts; extra == "common"
Provides-Extra: data-augmentation
Requires-Dist: nlpaug; extra == "data-augmentation"
Requires-Dist: nltk; extra == "data-augmentation"
Requires-Dist: textaugment; extra == "data-augmentation"
Requires-Dist: textblob<0.18,>=0.17; extra == "data-augmentation"
Requires-Dist: tika; extra == "data-augmentation"
Requires-Dist: torch; extra == "data-augmentation"
Requires-Dist: transformers; extra == "data-augmentation"
Provides-Extra: django
Requires-Dist: Django>=2.2; extra == "django"
Provides-Extra: docx
Requires-Dist: python-docx; extra == "docx"
Provides-Extra: epub
Requires-Dist: xml2epub; extra == "epub"
Provides-Extra: gcs
Requires-Dist: pathy[gcs]<0.12.0,>=0.10.0; extra == "gcs"
Provides-Extra: gif
Requires-Dist: WeasyPrint; extra == "gif"
Requires-Dist: pdf2image; extra == "gif"
Provides-Extra: images
Requires-Dist: imgkit; extra == "images"
Provides-Extra: mp3
Requires-Dist: gtts; extra == "mp3"
Requires-Dist: edge-tts; extra == "mp3"
Provides-Extra: odp
Requires-Dist: odfpy; extra == "odp"
Provides-Extra: ods
Requires-Dist: tablib; extra == "ods"
Requires-Dist: odfpy; extra == "ods"
Provides-Extra: odt
Requires-Dist: odfpy; extra == "odt"
Provides-Extra: pdf
Requires-Dist: pdfkit; extra == "pdf"
Requires-Dist: reportlab; extra == "pdf"
Provides-Extra: pptx
Requires-Dist: python-pptx; extra == "pptx"
Provides-Extra: s3
Requires-Dist: pathy[s3]<0.12.0,>=0.10.0; extra == "s3"
Provides-Extra: sftp
Requires-Dist: paramiko; extra == "sftp"
Provides-Extra: sqlalchemy
Requires-Dist: SQLAlchemy>=1.0; extra == "sqlalchemy"
Requires-Dist: SQLAlchemy-Utils>=0.37.0; extra == "sqlalchemy"
Provides-Extra: tiff
Requires-Dist: WeasyPrint; extra == "tiff"
Requires-Dist: pdf2image; extra == "tiff"
Provides-Extra: xlsx
Requires-Dist: tablib; extra == "xlsx"
Requires-Dist: openpyxl; extra == "xlsx"
